pyconfigs/__init__.py
pyconfigs-0.0.1.dev1.dist-info/METADATA
pyconfigs-0.0.1.dev1.dist-info/WHEEL
pyconfigs-0.0.1.dev1.dist-info/entry_points.txt
pyconfigs-0.0.1.dev1.dist-info/top_level.txt
pyconfigs-0.0.1.dev1.dist-info/RECORD
