Metadata-Version: 2.1
Name: pyconfigs
Version: 0.0.1.dev1
Summary: python configs
Home-page: UNKNOWN
Author: wanghuagang
Author-email: huagang517@126.com
License: UNKNOWN
Keywords: '["settings"]'
Platform: UNKNOWN
Classifier: Programming Language :: Python :: 3.7
